main.py
docker_recreate-1.1.0.dist-info/METADATA
docker_recreate-1.1.0.dist-info/WHEEL
docker_recreate-1.1.0.dist-info/entry_points.txt
docker_recreate-1.1.0.dist-info/top_level.txt
docker_recreate-1.1.0.dist-info/RECORD
