Metadata-Version: 2.1
Name: docker-recreate
Version: 1.1.0
Summary: Get docker run command from container
Home-page: https://www.github.com/jeffrey4l/docker-recreate
Author: Jeffrey Zhang
Author-email: zhang.lei.fly@gmail.com
License: UNKNOWN
Platform: UNKNOWN
